{"assets/icon.png":["assets/icon.png"],"assets/icons/.DS_Store":["assets/icons/.DS_Store"],"assets/icons/01.png":["assets/icons/01.png"],"assets/icons/02.png":["assets/icons/02.png"],"assets/icons/03.png":["assets/icons/03.png"],"assets/icons/04.png":["assets/icons/04.png"],"assets/icons/05.png":["assets/icons/05.png"],"assets/icons/06.png":["assets/icons/06.png"],"assets/icons/07.png":["assets/icons/07.png"],"assets/icons/08.png":["assets/icons/08.png"],"assets/icons/09.png":["assets/icons/09.png"],"assets/icons/10.png":["assets/icons/10.png"],"assets/icons/11.png":["assets/icons/11.png"],"assets/icons/12.png":["assets/icons/12.png"],"assets/icons/13.png":["assets/icons/13.png"],"assets/icons/14.png":["assets/icons/14.png"],"assets/icons/15.png":["assets/icons/15.png"],"assets/icons/16.png":["assets/icons/16.png"],"assets/icons/17.png":["assets/icons/17.png"],"assets/icons/18.png":["assets/icons/18.png"],"assets/icons/img1.png":["assets/icons/img1.png"],"assets/splash.png":["assets/splash.png"],"assets/subject.png":["assets/subject.png"],"packages/cupertino_icons/assets/CupertinoIcons.ttf":["packages/cupertino_icons/assets/CupertinoIcons.ttf"],"packages/flutter_inappwebview/assets/t_rex_runner/t-rex.css":["packages/flutter_inappwebview/assets/t_rex_runner/t-rex.css"],"packages/flutter_inappwebview/assets/t_rex_runner/t-rex.html":["packages/flutter_inappwebview/assets/t_rex_runner/t-rex.html"],"packages/youtube_player_flutter/assets/speedometer.webp":["packages/youtube_player_flutter/assets/speedometer.webp"]}